<?xml version="1.0"?>
<CLUFont version="1.0">
  <font face="bf" id="CLUFont_times_bf_25" mag_step="25" name="times">
    <sym b="2" h="48" id="97" id_is_num="1" w="45" x="0" y="0"/>
    <sym b="1" h="67" id="98" id_is_num="1" w="50" x="45" y="0"/>
    <sym b="2" h="48" id="99" id_is_num="1" w="40" x="95" y="0"/>
    <sym b="1" h="67" id="100" id_is_num="1" w="50" x="135" y="0"/>
    <sym b="1" h="47" id="101" id_is_num="1" w="40" x="185" y="0"/>
    <sym b="0" h="67" id="102" id_is_num="1" w="32" x="225" y="0"/>
    <sym b="20" h="66" id="103" id_is_num="1" w="44" x="257" y="0"/>
    <sym b="0" h="66" id="104" id_is_num="1" w="51" x="301" y="0"/>
    <sym b="0" h="67" id="105" id_is_num="1" w="24" x="352" y="0"/>
    <sym b="20" h="87" id="106" id_is_num="1" w="29" x="376" y="0"/>
    <sym b="0" h="66" id="107" id_is_num="1" w="51" x="405" y="0"/>
    <sym b="0" h="66" id="108" id_is_num="1" w="24" x="456" y="0"/>
    <sym b="0" h="46" id="109" id_is_num="1" w="78" x="480" y="0"/>
    <sym b="0" h="46" id="110" id_is_num="1" w="51" x="558" y="0"/>
    <sym b="1" h="47" id="111" id_is_num="1" w="45" x="609" y="0"/>
    <sym b="20" h="66" id="112" id_is_num="1" w="49" x="654" y="0"/>
    <sym b="20" h="66" id="113" id_is_num="1" w="49" x="703" y="0"/>
    <sym b="0" h="46" id="114" id_is_num="1" w="39" x="752" y="0"/>
    <sym b="1" h="47" id="115" id_is_num="1" w="33" x="791" y="0"/>
    <sym b="1" h="63" id="116" id_is_num="1" w="30" x="824" y="0"/>
    <sym b="2" h="47" id="117" id_is_num="1" w="52" x="854" y="0"/>
    <sym b="1" h="46" id="118" id_is_num="1" w="45" x="906" y="0"/>
    <sym b="1" h="46" id="119" id_is_num="1" w="67" x="951" y="0"/>
    <sym b="0" h="45" id="120" id_is_num="1" w="46" x="1018" y="0"/>
    <sym b="20" h="65" id="121" id_is_num="1" w="46" x="1064" y="0"/>
    <sym b="0" h="45" id="122" id_is_num="1" w="39" x="1110" y="0"/>
    <sym b="0" h="67" id="65" id_is_num="1" w="66" x="1149" y="0"/>
    <sym b="0" h="66" id="66" id_is_num="1" w="59" x="1215" y="0"/>
    <sym b="2" h="69" id="67" id_is_num="1" w="62" x="1274" y="0"/>
    <sym b="0" h="66" id="68" id_is_num="1" w="66" x="1336" y="0"/>
    <sym b="0" h="66" id="69" id_is_num="1" w="62" x="1402" y="0"/>
    <sym b="0" h="66" id="70" id_is_num="1" w="56" x="1464" y="0"/>
    <sym b="2" h="69" id="71" id_is_num="1" w="70" x="1520" y="0"/>
    <sym b="0" h="66" id="72" id_is_num="1" w="72" x="1590" y="0"/>
    <sym b="0" h="66" id="73" id_is_num="1" w="34" x="1662" y="0"/>
    <sym b="9" h="75" id="74" id_is_num="1" w="47" x="1696" y="0"/>
    <sym b="0" h="66" id="75" id_is_num="1" w="72" x="1743" y="0"/>
    <sym b="0" h="66" id="76" id_is_num="1" w="60" x="1815" y="0"/>
    <sym b="0" h="66" id="77" id_is_num="1" w="89" x="1875" y="0"/>
    <sym b="2" h="68" id="78" id_is_num="1" w="67" x="1964" y="0"/>
    <sym b="2" h="69" id="79" id_is_num="1" w="68" x="2031" y="0"/>
    <sym b="0" h="66" id="80" id_is_num="1" w="58" x="2099" y="0"/>
    <sym b="17" h="84" id="81" id_is_num="1" w="68" x="2157" y="0"/>
    <sym b="0" h="66" id="82" id_is_num="1" w="68" x="2225" y="0"/>
    <sym b="2" h="69" id="83" id_is_num="1" w="47" x="2293" y="0"/>
    <sym b="0" h="66" id="84" id_is_num="1" w="59" x="2340" y="0"/>
    <sym b="2" h="68" id="85" id_is_num="1" w="67" x="2399" y="0"/>
    <sym b="2" h="68" id="86" id_is_num="1" w="67" x="2466" y="0"/>
    <sym b="1" h="67" id="87" id_is_num="1" w="94" x="2533" y="0"/>
    <sym b="0" h="66" id="88" id_is_num="1" w="67" x="2627" y="0"/>
    <sym b="0" h="66" id="89" id_is_num="1" w="67" x="2694" y="0"/>
    <sym b="0" h="66" id="90" id_is_num="1" w="60" x="2761" y="0"/>
    <sym b="2" h="17" id="46" id_is_num="1" w="17" x="2821" y="0"/>
    <sym b="18" h="33" id="44" id_is_num="1" w="18" x="2838" y="0"/>
    <sym b="1" h="47" id="58" id_is_num="1" w="17" x="2856" y="0"/>
    <sym b="18" h="64" id="59" id_is_num="1" w="18" x="2873" y="0"/>
    <sym b="4" h="57" id="60" id_is_num="1" w="60" x="2891" y="0"/>
    <sym b="4" h="57" id="62" id_is_num="1" w="60" x="2951" y="0"/>
    <sym b="24" h="97" id="124" id_is_num="1" w="4" x="3011" y="0"/>
    <sym b="-16" h="12" id="45" id_is_num="1" w="24" x="3015" y="0"/>
    <sym b="-35" h="32" id="39" id_is_num="1" w="19" x="3039" y="0"/>
    <sym b="0" h="49" id="43" id_is_num="1" w="50" x="3058" y="0"/>
    <sym b="-25" h="42" id="42" id_is_num="1" w="39" x="3108" y="0"/>
    <sym b="1" h="68" id="63" id_is_num="1" w="39" x="3147" y="0"/>
    <sym b="14" h="80" id="91" id_is_num="1" w="23" x="3186" y="0"/>
    <sym b="14" h="80" id="93" id_is_num="1" w="23" x="3209" y="0"/>
    <sym b="17" h="85" id="40" id_is_num="1" w="26" x="3232" y="0"/>
    <sym b="17" h="85" id="41" id_is_num="1" w="26" x="3258" y="0"/>
    <sym b="-10" h="29" id="61" id_is_num="1" w="50" x="3284" y="0"/>
    <sym b="2" h="69" id="47" id_is_num="1" w="30" x="3334" y="0"/>
    <sym b="-34" h="33" id="34" id_is_num="1" w="45" x="3364" y="0"/>
    <sym b="1" h="68" id="33" id_is_num="1" w="17" x="3409" y="0"/>
    <sym b="2" h="69" id="64" id_is_num="1" w="70" x="3426" y="0"/>
    <sym b="-37" h="30" id="176" id_is_num="1" w="30" x="3496" y="0"/>
    <sym b="1" h="68" id="48" id_is_num="1" w="45" x="3526" y="0"/>
    <sym b="0" h="67" id="49" id_is_num="1" w="37" x="3571" y="0"/>
    <sym b="0" h="67" id="50" id_is_num="1" w="46" x="3608" y="0"/>
    <sym b="1" h="68" id="51" id_is_num="1" w="44" x="3654" y="0"/>
    <sym b="0" h="67" id="52" id_is_num="1" w="44" x="3698" y="0"/>
    <sym b="1" h="67" id="53" id_is_num="1" w="44" x="3742" y="0"/>
    <sym b="1" h="68" id="54" id_is_num="1" w="43" x="3786" y="0"/>
    <sym b="0" h="66" id="55" id_is_num="1" w="46" x="3829" y="0"/>
    <sym b="1" h="68" id="56" id_is_num="1" w="43" x="3875" y="0"/>
    <sym b="1" h="68" id="57" id_is_num="1" w="44" x="3918" y="0"/>
  </font>
</CLUFont>
